pilo/__init__.py
pilo/context.py
pilo/fields.py
pilo/source/__init__.py
pilo/source/configparser.py
pilo/source/default.py
pilo/source/json.py
pilo/source/mount.py
pilo/source/union.py
py3_pilo-0.4.0.dist-info/LICENSE
py3_pilo-0.4.0.dist-info/METADATA
py3_pilo-0.4.0.dist-info/WHEEL
py3_pilo-0.4.0.dist-info/top_level.txt
py3_pilo-0.4.0.dist-info/RECORD
