Metadata-Version: 2.1
Name: py3-pilo
Version: 0.4.0
Summary: Yet another form parser.
Home-page: https://github.com/bninja/pilo/
Author: egon
Author-email: egon@gb.com
License: Copyright (c) 2014 terrans.
Provides-Extra: tests
Requires-Dist: pytest (<3,>=2.5.2) ; extra == 'tests'
Requires-Dist: pytest-cov (<2,>=1.7) ; extra == 'tests'
Requires-Dist: mock (<2.0,>=1.0) ; extra == 'tests'
Requires-Dist: unittest2 (<0.6,>=0.5.1) ; extra == 'tests'
Requires-Dist: iso8601 (<0.2,>=0.1) ; extra == 'tests'
